matildapeak/chronicler/EventCategoryEnum_pb2.py
matildapeak/chronicler/EventMessage_pb2.py
matildapeak/chronicler/__init__.py
matildapeak_protobuf-2018.2.dist-info/METADATA
matildapeak_protobuf-2018.2.dist-info/RECORD
matildapeak_protobuf-2018.2.dist-info/WHEEL
matildapeak_protobuf-2018.2.dist-info/top_level.txt
