Metadata-Version: 2.1
Name: matildapeak-protobuf
Version: 2018.2
Summary: Cross-product protocol buffers
Home-page: https://gitlab.com/matilda.peak/protobuf
Author: Alan Christie
Author-email: alan.christie@matildapeak.com
License: MIT
Keywords: protobuf protoc messaging
Platform: any
Classifier: Development Status :: 5 - Production/Stable
Classifier: Environment :: Other Environment
Classifier: Intended Audience :: Developers
Classifier: License :: OSI Approved :: MIT License
Classifier: Programming Language :: Python :: 3.6
Classifier: Topic :: Software Development :: Libraries :: Python Modules
Classifier: Operating System :: POSIX :: Linux
Requires-Dist: protobuf (==3.3.0)
